cottoncandy/__init__.py
cottoncandy/appdirs.py
cottoncandy/backend.py
cottoncandy/browser.py
cottoncandy/defaults.cfg
cottoncandy/gdriveclient.py
cottoncandy/interfaces.py
cottoncandy/localclient.py
cottoncandy/options.py
cottoncandy/s3client.py
cottoncandy/utils.py
cottoncandy-0.3.0.dist-info/LICENSE
cottoncandy-0.3.0.dist-info/METADATA
cottoncandy-0.3.0.dist-info/WHEEL
cottoncandy-0.3.0.dist-info/top_level.txt
cottoncandy-0.3.0.dist-info/RECORD
