Metadata-Version: 2.1
Name: cottoncandy
Version: 0.3.0
Summary: sugar for S3
Home-page: http://gallantlab.github.io/cottoncandy/
Author: Anwar O. Nunez-Elizalde
Author-email: anwarnunez@gmail.com
License-File: LICENSE
Requires-Dist: PyDrive
Requires-Dist: boto3
Requires-Dist: botocore
Requires-Dist: python-dateutil
Requires-Dist: six
